yahoo_shopping/__init__.py
yahoo_shopping/__main__.py
yahoo_shopping/_main.py
yahoo_shopping/cli.py
yahoo_shopping/py.typed
yahoo_shopping-0.1.0.dist-info/LICENSE
yahoo_shopping-0.1.0.dist-info/METADATA
yahoo_shopping-0.1.0.dist-info/WHEEL
yahoo_shopping-0.1.0.dist-info/entry_points.txt
yahoo_shopping-0.1.0.dist-info/RECORD
