Metadata-Version: 2.1
Name: yahoo-shopping
Version: 0.1.0
Summary: Python API wrapper for Yahoo! ショッピング
Home-page: https://github.com/34j/yahoo-shopping
License: MIT
Author: 34j
Author-email: 34j.95a2p@simplelogin.com
Requires-Python: >=3.9,<4.0
Classifier: Development Status :: 2 - Pre-Alpha
Classifier: Intended Audience :: Developers
Classifier: License :: OSI Approved :: MIT License
Classifier: Natural Language :: English
Classifier: Operating System :: OS Independent
Classifier: Programming Language :: Python :: 3
Classifier: Programming Language :: Python :: 3.9
Classifier: Programming Language :: Python :: 3.10
Classifier: Programming Language :: Python :: 3.11
Classifier: Programming Language :: Python :: 3.12
Classifier: Topic :: Software Development :: Libraries
Requires-Dist: aiohttp-client-cache (>=0.11.1,<0.12.0)
Requires-Dist: aiosqlite (>=0.20.0,<0.21.0)
Requires-Dist: attrs (>=24.2.0,<25.0.0)
Requires-Dist: cyclopts (>=2.9.9,<3.0.0)
Requires-Dist: fake-useragent (>=1.5.1,<2.0.0)
Requires-Dist: lxml (>=5.3.0,<6.0.0)
Requires-Dist: nest-asyncio (>=1.6.0,<2.0.0)
Requires-Dist: rich (>=10)
Requires-Dist: selenium-driverless (>=1.9.3.1,<2.0.0.0)
Requires-Dist: shelved-cache (>=0.3.1,<0.4.0)
Requires-Dist: tenacity (>=9.0.0,<10.0.0)
Requires-Dist: typing-extensions (>=4.12.2,<5.0.0)
Project-URL: Bug Tracker, https://github.com/34j/yahoo-shopping/issues
Project-URL: Changelog, https://github.com/34j/yahoo-shopping/blob/main/CHANGELOG.md
Project-URL: Documentation, https://yahoo-shopping.readthedocs.io
Project-URL: Repository, https://github.com/34j/yahoo-shopping
